ui_feedback_parser/__init__.py
ui_feedback_parser/main.py
ui_feedback_parser/prompts.py
ui_feedback_parser-2025.12.21172537.dist-info/METADATA
ui_feedback_parser-2025.12.21172537.dist-info/WHEEL
ui_feedback_parser-2025.12.21172537.dist-info/top_level.txt
ui_feedback_parser-2025.12.21172537.dist-info/RECORD
