Metadata-Version: 2.4
Name: ui-feedback-parser
Version: 2025.12.21172537
Summary: A new package is designed to analyze user-submitted discussions or problem descriptions about improving business interfaces, such as Chase Travel's UI. It processes the input text and outputs a struct
Author-email: ui-feedback-parser <hi@eugene.plus>
License: MIT
Project-URL: Homepage, https://github.com/chigwell/ui-feedback-parser
Requires-Python: >=3.9
Requires-Dist: langchain-llm7>=0.0.0
Requires-Dist: llmatch-messages>=0.0.0
Requires-Dist: langchain-core>=0.3.0
